pigz_python/__init__.py
pigz_python/pigz_python.py
tests/__init__.py
tests/test_pigz_python.py
pigz_python-1.0.1.dist-info/LICENSE
pigz_python-1.0.1.dist-info/METADATA
pigz_python-1.0.1.dist-info/WHEEL
pigz_python-1.0.1.dist-info/top_level.txt
pigz_python-1.0.1.dist-info/RECORD
