Metadata-Version: 2.1
Name: pigz-python
Version: 1.0.1
Summary: A pure Python implementation of the pigz utility.
Home-page: https://github.com/nix7drummer88/pigz-python
Author: Ben Guise
Author-email: bguise135@gmail.com
Maintainer: Ben Guise
Maintainer-email: bguise135@gmail.com
License: MIT
Keywords: zip gzip compression
Platform: UNKNOWN
Classifier: Development Status :: 3 - Alpha
Classifier: Intended Audience :: End Users/Desktop
Classifier: Intended Audience :: Developers
Classifier: Intended Audience :: System Administrators
Classifier: Topic :: Utilities
